entropy/__init__.py
entropy/entro.py
entropy/py.typed
entropy_calculator-0.0.1.dist-info/METADATA
entropy_calculator-0.0.1.dist-info/WHEEL
entropy_calculator-0.0.1.dist-info/entry_points.txt
entropy_calculator-0.0.1.dist-info/top_level.txt
entropy_calculator-0.0.1.dist-info/RECORD
