Metadata-Version: 2.1
Name: entropy-calculator
Version: 0.0.1
Summary: Calculate entropy
Home-page: https://github.com/fionn/entropy
Author: Fionn Fitzmaurice
Project-URL: Source Code, https://github.com/fionn/entropy
Project-URL: Changelog, https://github.com/fionn/entropy/tags
Project-URL: Documentation, https://github.com/fionn/entropy/blob/master/README.md
Project-URL: Bug Tracker, https://github.com/fionn/entropy/issues
Project-URL: PyPI, https://pypi.org/project/entropy/
Project-URL: Download, https://github.com/fionn/entropy/archive/refs/heads/master.zip
Classifier: Programming Language :: Python :: 3
Classifier: Development Status :: 4 - Beta
Classifier: Intended Audience :: Developers
Classifier: Topic :: Security
Classifier: Typing :: Typed
Requires-Python: >=3.9
Provides-Extra: dev
Requires-Dist: pylint ; extra == 'dev'
Requires-Dist: mypy ; extra == 'dev'
